postcards/postcards.py
postcards/__init__.py
postcards/template_config.json
postcards/plugin_chuck_norris/__init__.py
postcards/plugin_chuck_norris/postcards_chuck_norris.py
postcards/plugin_chuck_norris/chuck_norris_jokes.json
postcards/plugin_random/postcards_random.py
postcards/plugin_random/__init__.py
postcards/plugin_random/random_search_term/__init__.py
postcards/plugin_random/random_search_term/random_search_term.py
postcards/plugin_random/util/__init__.py
postcards/plugin_random/util/bing_image_scraper.py
postcards/plugin_folder/postcards_folder.py
postcards/plugin_folder/__init__.py
postcards/plugin_folder/slice_image.py
postcards/plugin_pexels/postcards_pexels.py
postcards/plugin_pexels/__init__.py
postcards/plugin_pexels/util/pexels.py
postcards/plugin_pexels/util/__init__.py
postcards/plugin_pexels/util/words.txt
postcards-0.0.8.dist-info/RECORD
postcards-0.0.8.dist-info/metadata.json
postcards-0.0.8.dist-info/WHEEL
postcards-0.0.8.dist-info/entry_points.txt
postcards-0.0.8.dist-info/DESCRIPTION.rst
postcards-0.0.8.dist-info/top_level.txt
postcards-0.0.8.dist-info/METADATA
