Metadata-Version: 2.0
Name: postcards
Version: 0.0.8
Summary: A CLI for the Swiss Postcard Creator
Home-page: http://github.com/abertschi/postcards
Author: Andrin Bertschi
Author-email: UNKNOWN
License: UNKNOWN
Keywords: postcard swiss
Platform: any
Requires-Dist: beautifulsoup4 (==4.6.0)
Requires-Dist: certifi (==2017.11.5)
Requires-Dist: chardet (==3.0.4)
Requires-Dist: cookies (==2.2.1)
Requires-Dist: idna (==2.6)
Requires-Dist: inflection (==0.3.1)
Requires-Dist: Js2Py (==0.50)
Requires-Dist: nltk (==3.2.5)
Requires-Dist: olefile (==0.44)
Requires-Dist: Pillow (==4.3.0)
Requires-Dist: postcard-creator (==0.0.8)
Requires-Dist: pyjsparser (==2.5.2)
Requires-Dist: python-resize-image (==1.1.11)
Requires-Dist: pytz (==2017.3)
Requires-Dist: requests (==2.18.4)
Requires-Dist: requests-toolbelt (==0.8.0)
Requires-Dist: six (==1.11.0)
Requires-Dist: tzlocal (==1.4)
Requires-Dist: urllib3 (==1.22)
